django_anger
