Metadata-Version: 1.1
Name: django-anger
Version: 0.1-20130513
Summary: tools and hacks for using Django _in anger_
Home-page: https://github.com/cberzan/django-anger
Author: Constantin Berzan
Author-email: cberzan@gmail.com
License: MIT
Keywords: django south migration migrations
Platform: UNKNOWN
Classifier: Development Status :: 3 - Alpha
Classifier: Intended Audience :: Developers
Classifier: License :: OSI Approved :: MIT License
Classifier: Operating System :: OS Independent
Classifier: Programming Language :: Python :: 2.7
